setup.py
django_openbudget.egg-info/PKG-INFO
django_openbudget.egg-info/SOURCES.txt
django_openbudget.egg-info/dependency_links.txt
django_openbudget.egg-info/not-zip-safe
django_openbudget.egg-info/requires.txt
django_openbudget.egg-info/top_level.txt
openbudgetapp/__init__.py
openbudgetapp/admin.py
openbudgetapp/urls.py
openbudgetapp/api/__init__.py
openbudgetapp/api/openbudgetapi.py
openbudgetapp/forms/__init__.py
openbudgetapp/forms/accountset.py
openbudgetapp/management/__init__.py
openbudgetapp/management/commands/__init__.py
openbudgetapp/management/commands/gnucash-import.py
openbudgetapp/management/commands/redmine-import.py
openbudgetapp/management/commands/tagger-export.py
openbudgetapp/migrations/0001_initial.py
openbudgetapp/migrations/0002_auto__add_receipt__add_project__add_client.py
openbudgetapp/migrations/0003_auto__add_receiptexpense.py
openbudgetapp/migrations/0004_auto__add_field_transaction_num.py
openbudgetapp/migrations/0005_auto__add_field_receiptexpense_vendor__add_field_receiptexpense_vat__a.py
openbudgetapp/migrations/0006_auto__add_accountset__add_field_account_accountset.py
openbudgetapp/migrations/0007_auto__add_field_transaction_accountset__add_field_split_accountset.py
openbudgetapp/migrations/0008_auto__add_field_accountset_gnucashdb.py
openbudgetapp/migrations/0009_auto__chg_field_accountset_gnucashdb.py
openbudgetapp/migrations/0010_auto__add_field_accountset_group.py
openbudgetapp/migrations/0011_auto__add_field_account_code.py
openbudgetapp/migrations/__init__.py
openbudgetapp/models/__init__.py
openbudgetapp/models/account.py
openbudgetapp/models/accountbudget.py
openbudgetapp/models/accountextra.py
openbudgetapp/models/accountset.py
openbudgetapp/models/client.py
openbudgetapp/models/inflationrate.py
openbudgetapp/models/project.py
openbudgetapp/models/receipt.py
openbudgetapp/models/receiptexpense.py
openbudgetapp/models/split.py
openbudgetapp/models/transaction.py
openbudgetapp/templates/__init__.py
openbudgetapp/templatetags/__init__.py
openbudgetapp/templatetags/openbudgetapp_extras.py
openbudgetapp/templatetags/pyformat.py
openbudgetapp/tests/__init__.py
openbudgetapp/tests/tests.py
openbudgetapp/utils/__init__.py
openbudgetapp/utils/export.py
