Metadata-Version: 1.0
Name: django-openbudget
Version: 0.1.0
Summary: 
